{
  "schemaVersion": "",
  "version": "",
  "displayName": "",
  "description": "",
  "format": "JSON",
  "model": {
    "model": {
      "version": {
        "0": ""
      }
    },
    "registrant": {},
    "category": {
      "name": "Uncategorized"
    },
    "subCategory": "Uncategorized",
    "metadata": {
      "capabilities": {
        "items": {
          "kind": {},
          "entityState": {},
          "status": "enabled"
        }
      },
      "primaryColor": "#00b39f",
      "secondaryColor": "#00D3A9",
      "shape": "circle"
    }
  },
  "registrant": {},
  "metadata": {
    "genealogy": "",
    "shape": "",
    "primaryColor": "",
    "secondaryColor": "",
    "svgWhite": "",
    "svgColor": "",
    "svgComplete": "",
    "status": ""
  },
  "category": {},
  "capabilities": {},
  "component": {
    "version": "",
    "kind": "",
    "schema": ""
  }
}